opentimelineio_plugins/__init__.py
opentimelineio_plugins-0.18.1.dist-info/METADATA
opentimelineio_plugins-0.18.1.dist-info/WHEEL
opentimelineio_plugins-0.18.1.dist-info/licenses/LICENSE
opentimelineio_plugins-0.18.1.dist-info/RECORD
