Metadata-Version: 2.4
Name: OpenTimelineIO-Plugins
Version: 0.18.1
Summary: OpenTimelineIO with batteries included plug-ins.
Project-URL: Homepage, https://opentimeline.io
Project-URL: Tracker, https://github.com/OpenTimelineIO/OpenTimelineIO-Plugins/issues
Author-email: Contributors to the OpenTimelineIO project <otio-discussion@lists.aswf.io>
License: 
License-File: LICENSE
Keywords: edit,editing,editorial,film,non-linear,otio,otio-adapter,time,tv
Classifier: Development Status :: 5 - Production/Stable
Classifier: License :: OSI Approved :: Apache Software License
Classifier: Natural Language :: English
Classifier: Operating System :: OS Independent
Classifier: Programming Language :: Python :: 3
Classifier: Programming Language :: Python :: 3.7
Classifier: Programming Language :: Python :: 3.8
Classifier: Programming Language :: Python :: 3.9
Classifier: Programming Language :: Python :: 3.10
Classifier: Programming Language :: Python :: 3.11
Classifier: Topic :: Multimedia :: Graphics
Classifier: Topic :: Multimedia :: Video
Classifier: Topic :: Multimedia :: Video :: Display
Classifier: Topic :: Multimedia :: Video :: Non-Linear Editor
Classifier: Topic :: Software Development :: Libraries :: Python Modules
Requires-Python: >=3.7
Requires-Dist: opentimelineio==0.18.1
Requires-Dist: otio-aaf-adapter
Requires-Dist: otio-ale-adapter
Requires-Dist: otio-burnins-adapter
Requires-Dist: otio-cmx3600-adapter
Requires-Dist: otio-fcp-adapter
Requires-Dist: otio-maya-sequencer-adapter
Requires-Dist: otio-svg-adapter
Requires-Dist: otio-xges-adapter
